fssh/__init__.py
fssh/__main__.py
fssh/setup.py
fssh-1.0.8.dist-info/LICENSE
fssh-1.0.8.dist-info/METADATA
fssh-1.0.8.dist-info/WHEEL
fssh-1.0.8.dist-info/entry_points.txt
fssh-1.0.8.dist-info/top_level.txt
fssh-1.0.8.dist-info/RECORD
